miroflowexport/__init__.py
miroflowexport/miroaccess.py
miroflowexport/internal/__init__.py
miroflowexport/internal/excelcolumns.py
miroflowexport/internal/exporter.py
miroflowexport/internal/logobfuscate.py
miroflowexport/internal/miroaccess.py
miroflowexport/internal/plan.py
miroflowexport/internal/sanitize.py
miroflowexport/internal/task.py
miroflowexport/internal/transform.py
miroflowexport/internal/versions/__init__.py
miroflowexport/internal/versions/common.py
miroflowexport/internal/versions/version_0.py
miroflowexport/internal/versions/version_1.py
miroflowexport-1.4.1.dist-info/METADATA
miroflowexport-1.4.1.dist-info/WHEEL
miroflowexport-1.4.1.dist-info/top_level.txt
miroflowexport-1.4.1.dist-info/RECORD
