Metadata-Version: 2.1
Name: miroflowexport
Version: 1.4.1
Summary: Derive a Gantt-like plan from Miro sticky note workflow
Home-page: https://gitlab.com/sven.flake/miroflowexport
Author: Sven Flake
Author-email: sven.flake@gmail.com
Requires-Dist: flexlog (==1.5.0)
Requires-Dist: coolname (==1.1.0)
Requires-Dist: openpyxl (==3.0.9)
Requires-Dist: requests (==2.27.1)
